signchart/__init__.py
signchart/signchart.py
signchart-0.2.2.dist-info/licenses/LICENSE
signchart-0.2.2.dist-info/METADATA
signchart-0.2.2.dist-info/WHEEL
signchart-0.2.2.dist-info/top_level.txt
signchart-0.2.2.dist-info/RECORD
