Metadata-Version: 2.4
Name: signchart
Version: 0.2.2
Summary: Automatically generates sign charts for polynomial functions and rational functions.
Home-page: https://github.com/reneaas/signchart
Author: René Alexander Ask
Author-email: rene.ask@icloud.com
Classifier: Programming Language :: Python :: 3
Classifier: License :: OSI Approved :: MIT License
Classifier: Operating System :: OS Independent
Requires-Python: >=3.7
License-File: LICENSE
Requires-Dist: numpy
Requires-Dist: matplotlib
Requires-Dist: sympy
Requires-Dist: plotmath>=0.2.18
Dynamic: author
Dynamic: author-email
Dynamic: classifier
Dynamic: description
Dynamic: description-content-type
Dynamic: home-page
Dynamic: license-file
Dynamic: requires-dist
Dynamic: requires-python
Dynamic: summary
